mylib_027/__init__.py
mylib_027-0.1.dist-info/LICENSE.txt
mylib_027-0.1.dist-info/METADATA
mylib_027-0.1.dist-info/WHEEL
mylib_027-0.1.dist-info/top_level.txt
mylib_027-0.1.dist-info/RECORD
